metro2D/__init__.py
metro2D/main.py
metro2D/images/__init__.py
metro2D/images/pl.png
metro2D/images/raman.png
metro2D/images/sem.png
metro2D/images/wdxrf.png
metro2d-1.0.2.dist-info/licenses/LICENSE
metro2d-1.0.2.dist-info/METADATA
metro2d-1.0.2.dist-info/WHEEL
metro2d-1.0.2.dist-info/entry_points.txt
metro2d-1.0.2.dist-info/top_level.txt
metro2d-1.0.2.dist-info/RECORD
